mindie_turbo/__init__.py
mindie_turbo/_ops.cpython-311-aarch64-linux-gnu.so
mindie_turbo/env.py
mindie_turbo/libturbo_kernels.so
mindie_turbo/turbo_torch.cpython-311-aarch64-linux-gnu.so
mindie_turbo/version.py
mindie_turbo/adaptor/__init__.py
mindie_turbo/adaptor/base_turbo.py
mindie_turbo/adaptor/vllm_turbo.py
mindie_turbo/adaptor/vllm/__init__.py
mindie_turbo/adaptor/vllm/attention.py
mindie_turbo/adaptor/vllm/layernorm.py
mindie_turbo/adaptor/vllm/ops.py
mindie_turbo/adaptor/vllm/quantize.py
mindie_turbo/adaptor/vllm/sampler.py
mindie_turbo/adaptor/vllm/weight_utils.py
mindie_turbo/adaptor/vllm/distributed/__init__.py
mindie_turbo/adaptor/vllm/distributed/parallel_state.py
mindie_turbo/adaptor/vllm/model_executor/__init__.py
mindie_turbo/adaptor/vllm/model_executor/linear.py
mindie_turbo/adaptor/vllm/model_executor/logits_processor.py
mindie_turbo/distributed/__init__.py
mindie_turbo/distributed/lccl_communication.py
mindie_turbo/functional/__init__.py
mindie_turbo/functional/activation.py
mindie_turbo/multimodal/__init__.py
mindie_turbo/multimodal/akpp/__init__.py
mindie_turbo/multimodal/akpp/image_processing_qwen2_vl.py
mindie_turbo/multimodal/akpp/image_processing_utils.py
mindie_turbo/multimodal/fastpatch/__init__.py
mindie_turbo/multimodal/fastpatch/conv2mat.py
mindie_turbo/multimodal/mmdist/__init__.py
mindie_turbo/multimodal/mmdist/comm.py
mindie_turbo/multimodal/mmdist/qwen2_vl_vit.py
mindie_turbo/multimodal/mmdist/utils.py
mindie_turbo/multimodal/mmzip/__init__.py
mindie_turbo/multimodal/mmzip/manager.py
mindie_turbo/quantize/__init__.py
mindie_turbo/quantize/faquant.py
mindie_turbo/quantize/quant_utils.py
mindie_turbo/quantize/quantizer.py
mindie_turbo/quantize/w8a8.py
mindie_turbo/quantize/w8a8_dynamic.py
mindie_turbo/utils/__init__.py
mindie_turbo/utils/cli.py
mindie_turbo/utils/logger.py
mindie_turbo/utils/patcher.py
mindie_turbo-2.0rc1.dist-info/LICENSE
mindie_turbo-2.0rc1.dist-info/METADATA
mindie_turbo-2.0rc1.dist-info/WHEEL
mindie_turbo-2.0rc1.dist-info/top_level.txt
mindie_turbo-2.0rc1.dist-info/RECORD
