Metadata-Version: 2.1
Name: mindie_turbo
Version: 2.0rc1
Summary: MindIE Turbo: An LLM inference acceleration framework featuring extensive plugin collections optimized for Ascend devices.
Home-page: https://www.hiascend.com/ 
Author: ascend
License: Apache 2.0
Project-URL: Homepage, https://www.hiascend.com/
Project-URL: Documentation, https://www.hiascend.com/
Classifier: Programming Language :: Python :: 3.9
Classifier: Programming Language :: Python :: 3.10
Classifier: Programming Language :: Python :: 3.11
Classifier: Programming Language :: Python :: 3.12
Classifier: Topic :: Scientific/Engineering :: Artificial Intelligence
Requires-Python: >=3.9
License-File: LICENSE
Requires-Dist: filelock ==3.16.1
Requires-Dist: fsspec ==2024.12.0
Requires-Dist: jinja2 ==3.1.5
Requires-Dist: markupsafe ==3.0.2
Requires-Dist: mpmath ==1.3.0
Requires-Dist: networkx ==3.4.2
Requires-Dist: sympy ==1.13.1
Requires-Dist: torch ==2.5.1
Requires-Dist: typing-extensions ==4.12.2
